[
	{
		"model":"crises.CrisesLinks",
		"pk":1,
		"fields":{
			"external_links":"http://www.nad-plo.org/",
			"crisis":1
		}
	},
	{
		"model":"crises.CrisesLinks",
		"pk":2,
		"fields":{
			"external_links":"http://www.un.org/ha/chernobyl/docs/report.pdf",
			"crisis":2
		}
	},
	{
		"model":"crises.CrisesLinks",
		"pk":3,
		"fields":{
			"external_links":"http://ptwc.weather.gov/",
			"crisis":3
		}
	},
	{
		"model":"crises.CrisesLinks",
		"pk":4,
		"fields":{
			"external_links":"http://www.bmhrc.org/Bhopal%20Gas%20Tragedy.htm",
			"crisis":4
		}
	},
	{
		"model":"crises.CrisesLinks",
		"pk":5,
		"fields":{
			"external_links":"http://earthquake.usgs.gov/regional/nca/1989/",
			"crisis":5
		}
	}
]