[{"text": "mandatory", "size": 32.25806451612903}, {"text": "reference", "size": 32.25806451612903}, {"text": "century", "size": 32.25806451612903}, {"text": "rule", "size": 32.25806451612903}, {"text": "wider", "size": 32.25806451612903}, {"text": "israeli", "size": 96.7741935483871}, {"text": "palestinian", "size": 64.51612903225806}, {"text": "began", "size": 32.25806451612903}, {"text": "zionist", "size": 32.25806451612903}, {"text": "mid", "size": 32.25806451612903}, {"text": "between", "size": 64.51612903225806}, {"text": "palestine", "size": 32.25806451612903}, {"text": "formed", "size": 32.25806451612903}, {"text": "ranging", "size": 32.25806451612903}, {"text": "conflict", "size": 161.29032258064515}, {"text": "yishuv", "size": 32.25806451612903}, {"text": "core", "size": 32.25806451612903}, {"text": "used", "size": 32.25806451612903}, {"text": "earlier", "size": 32.25806451612903}, {"text": "arab", "size": 64.51612903225806}, {"text": "part", "size": 32.25806451612903}, {"text": "israelis", "size": 32.25806451612903}, {"text": "struggle", "size": 32.25806451612903}, {"text": "population", "size": 32.25806451612903}, {"text": "wide", "size": 32.25806451612903}, {"text": "term", "size": 32.25806451612903}, {"text": "sometimes", "size": 32.25806451612903}, {"text": "sectarian", "size": 32.25806451612903}, {"text": "british", "size": 32.25806451612903}, {"text": "ongoing", "size": 32.25806451612903}, {"text": "palestinians", "size": 32.25806451612903}]